{"id":"466c2e14-c78a-4b56-b2ca-03323de49147","image":"https://s3.amazonaws.com/uifaces/faces/twitter/umurgdk/128.jpg","color":"#791946","name":"Isom Beatty MD","email":"Maynard18@yahoo.com","address":{"zipCode":"57214-5939","city":"Roobland","cityPrefix":"New","citySuffix":"town","streetName":"Jessyca Lakes","streetAddress":"9011 Darrel Underpass","streetSuffix":"Cape","streetPrefix":"a","secondaryAddress":"Apt. 994","county":"Bedfordshire","country":"Mali","state":"New Jersey","latitude":"15.0054","longitude":"138.6344"},"company":null,"friends":["d154abb6-c106-4412-8b54-777c3353c7df","44a8e7fc-bc79-48ef-a67d-8068d708b6d7"]}