{"id":"67618c63-3554-4e98-a89e-9974b597e6cb","image":"https://s3.amazonaws.com/uifaces/faces/twitter/lowie/128.jpg","color":"#341964","name":"Yvette Pfeffer","email":"Domenico46@gmail.com","address":{"zipCode":"05828-3088","city":"West Muhammad","cityPrefix":"Lake","citySuffix":"port","streetName":"Parker Courts","streetAddress":"69692 Goyette Via","streetSuffix":"Springs","streetPrefix":"c","secondaryAddress":"Apt. 679","county":"Borders","country":"Fiji","state":"New Mexico","latitude":"78.5827","longitude":"-96.5709"},"company":"d61baea5-2431-41b3-859e-d77fa291f448","friends":["a8b9fd4c-3430-4a1e-9371-88f6a5416b9a"]}