{"id":"6fbb100b-e3e2-47df-b2c9-19a85678816b","image":"https://s3.amazonaws.com/uifaces/faces/twitter/imammuht/128.jpg","color":"#801058","name":"Rowland Skiles","email":"Elise5@hotmail.com","address":{"zipCode":"93118-5951","city":"South Avisland","cityPrefix":"West","citySuffix":"ton","streetName":"Rosalyn Unions","streetAddress":"90786 Windler Rue","streetSuffix":"Mountain","streetPrefix":"b","secondaryAddress":"Apt. 790","county":"Cambridgeshire","country":"Puerto Rico","state":"South Carolina","latitude":"22.1579","longitude":"24.4514"},"company":null,"friends":["434e9385-5cb2-4729-bc18-6cfe9e84f918","015ca2e0-533e-43c2-873b-3398c09aacd9","44cc6d3a-8199-41a9-94af-0ae8bbdf1c69","434e9385-5cb2-4729-bc18-6cfe9e84f918"]}