{"id":"925f9c53-ddac-4984-a487-c021954822d7","image":"https://s3.amazonaws.com/uifaces/faces/twitter/osmond/128.jpg","color":"#662825","name":"Vickie Bradtke I","email":"Alvis_VonRueden@gmail.com","address":{"zipCode":"35451-5515","city":"Port Walkerton","cityPrefix":"New","citySuffix":"berg","streetName":"Pfeffer Villages","streetAddress":"6874 Stanley Via","streetSuffix":"Dale","streetPrefix":"c","secondaryAddress":"Apt. 912","county":"Berkshire","country":"Honduras","state":"Texas","latitude":"-73.2555","longitude":"-151.5901"},"company":null,"friends":["d4821d27-8278-451e-bc00-ffdb39757fdf","0fee820e-f9a5-4863-8cf8-ebb0f3fdcb49","8df062dd-7644-4680-ab73-fec7360ec7da"]}