{"id":"ac2aa594-e1ba-404b-8bdb-7c1a01ce7fca","image":"https://s3.amazonaws.com/uifaces/faces/twitter/imcoding/128.jpg","color":"#31793b","name":"Madilyn Tremblay V","email":"Nestor_Will57@gmail.com","address":{"zipCode":"66026-3996","city":"Lake Cesarmouth","cityPrefix":"Lake","citySuffix":"mouth","streetName":"Karina Turnpike","streetAddress":"71076 Witting Crossroad","streetSuffix":"Mission","streetPrefix":"b","secondaryAddress":"Apt. 942","county":"Avon","country":"Sudan","state":"North Dakota","latitude":"-38.5230","longitude":"85.1134"},"company":null,"friends":["15df97d8-49e9-43fa-a13b-0eca95566995","3768d916-00a0-4517-9c7c-37061010221f","6729e56f-4bca-4061-b0c1-9b414c76f524"]}