{"id":"b36690f5-1ed9-4420-9845-d26e54949571","image":"https://s3.amazonaws.com/uifaces/faces/twitter/dutchnadia/128.jpg","color":"#073764","name":"Beverly Brakus","email":"Kari.Kessler8@gmail.com","address":{"zipCode":"02672-0810","city":"Rickieton","cityPrefix":"Port","citySuffix":"side","streetName":"Jordon Passage","streetAddress":"714 Stephen Green","streetSuffix":"Plains","streetPrefix":"c","secondaryAddress":"Suite 149","county":"Berkshire","country":"Niue","state":"Minnesota","latitude":"-28.6196","longitude":"-2.5894"},"company":"5fd82a94-c61e-455c-a4ee-c22b5b955520","friends":["be9ad054-091c-4463-91bc-c3515af9edfd","6cf33ad1-e9bd-4b7e-91fa-f5620b68893e"]}