{"id":"c1190ab8-df6b-48f1-a0bb-b6edc388f05c","image":"https://s3.amazonaws.com/uifaces/faces/twitter/gu5taf/128.jpg","color":"#485c33","name":"Cheyanne Greenfelder","email":"Bernie_Schuster54@gmail.com","address":{"zipCode":"53138","city":"New Garnetmouth","cityPrefix":"North","citySuffix":"ville","streetName":"Marquis Prairie","streetAddress":"37724 Sabryna Forges","streetSuffix":"Vista","streetPrefix":"b","secondaryAddress":"Apt. 259","county":"Borders","country":"Seychelles","state":"New York","latitude":"81.8518","longitude":"-153.9842"},"company":null,"friends":["4b66b43a-2cc4-46ab-a5cb-c7789f8ab712","5f0acf58-dca0-4c23-864f-7be6aba0d953","db3fc417-b181-4990-80bc-b40199698acd","f4a7e73c-8c89-4e91-9fe0-acd96402bcf1"]}