{"id":"fdebacac-e079-45da-9256-34d9b2f70266","image":"https://s3.amazonaws.com/uifaces/faces/twitter/the_winslet/128.jpg","color":"#4c3975","name":"Lourdes Lowe","email":"Rowena27@gmail.com","address":{"zipCode":"61731-7489","city":"South Sigurdstad","cityPrefix":"North","citySuffix":"haven","streetName":"Silas Drives","streetAddress":"72872 Collier Islands","streetSuffix":"Crossing","streetPrefix":"a","secondaryAddress":"Apt. 012","county":"Berkshire","country":"Bouvet Island (Bouvetoya)","state":"Nevada","latitude":"-31.6168","longitude":"-172.4109"},"company":"2f43f7fe-0271-46d6-84bb-9c574e42c935","friends":["ce88a408-6dd4-472d-a7ad-59fbacfcb771"]}