{"id":"0fa9eff7-d31a-4801-8b19-15ae9fa9efed","color":"#6c1639","image":"http://lorempixel.com/640/480/business","name":"Kunde - Ebert","suffice":"and Sons","catchPhrase":"Extended disintermediate help-desk","bs":"B2B leverage applications","address":{"zipCode":"03493","city":"Lake Mohamed","cityPrefix":"North","citySuffix":"furt","streetName":"Shawn Prairie","streetAddress":"6625 Melvina Circle","streetSuffix":"Motorway","streetPrefix":"c","secondaryAddress":"Suite 476","county":"Cambridgeshire","country":"Finland","state":"Ohio","latitude":"-57.2131","longitude":"111.5699"}}