{"id":"12c99fef-aaf6-4bff-bbed-fe17c3de7782","color":"#236017","image":"http://lorempixel.com/640/480/business","name":"Zboncak - Christiansen","suffice":"Inc","catchPhrase":"Down-sized tertiary moratorium","bs":"open-source seize e-services","address":{"zipCode":"09855","city":"Dooleychester","cityPrefix":"North","citySuffix":"land","streetName":"Adolph Forges","streetAddress":"623 Candice Freeway","streetSuffix":"Underpass","streetPrefix":"a","secondaryAddress":"Apt. 447","county":"Berkshire","country":"Croatia","state":"Maine","latitude":"-33.5086","longitude":"21.9860"}}