{"id":"13d7be14-5295-4a50-a9a1-fbd14547c612","color":"#460675","image":"http://lorempixel.com/640/480/business","name":"Witting LLC","suffice":"Inc","catchPhrase":"Innovative encompassing customer loyalty","bs":"impactful brand vortals","address":{"zipCode":"11659","city":"East Lyla","cityPrefix":"South","citySuffix":"stad","streetName":"Bernier Bypass","streetAddress":"5936 Strosin Ford","streetSuffix":"Harbors","streetPrefix":"c","secondaryAddress":"Apt. 676","county":"Avon","country":"Kuwait","state":"Mississippi","latitude":"30.0411","longitude":"-10.6923"}}