{"id":"295b27ed-6a41-491c-bed1-9da2da30e23c","color":"#093377","image":"http://lorempixel.com/640/480/business","name":"Goodwin, Satterfield and Reinger","suffice":"LLC","catchPhrase":"Virtual cohesive Graphic Interface","bs":"B2B matrix bandwidth","address":{"zipCode":"64942-9316","city":"Cronashire","cityPrefix":"New","citySuffix":"port","streetName":"Marlee Brooks","streetAddress":"028 Melvin Squares","streetSuffix":"Street","streetPrefix":"a","secondaryAddress":"Suite 880","county":"Borders","country":"Brazil","state":"New York","latitude":"-10.6278","longitude":"139.1423"}}