{"id":"2ed5c853-687b-4a7a-a98e-bb4b7e63ae1e","color":"#602e73","image":"http://lorempixel.com/640/480/business","name":"Osinski, Altenwerth and Johns","suffice":"LLC","catchPhrase":"Synchronised zero tolerance architecture","bs":"interactive streamline experiences","address":{"zipCode":"24944-4538","city":"North Raymouth","cityPrefix":"Port","citySuffix":"port","streetName":"Natalie Mission","streetAddress":"70093 Lindgren Dam","streetSuffix":"Corner","streetPrefix":"a","secondaryAddress":"Suite 248","county":"Avon","country":"Montserrat","state":"Idaho","latitude":"29.1949","longitude":"39.2693"}}