{"id":"33ffbab5-9ba3-4396-9169-25662e6624ae","color":"#400a07","image":"http://lorempixel.com/640/480/business","name":"Zemlak Inc","suffice":"and Sons","catchPhrase":"Multi-tiered cohesive framework","bs":"e-business benchmark vortals","address":{"zipCode":"92617-0115","city":"Ninamouth","cityPrefix":"Lake","citySuffix":"berg","streetName":"Kali Lake","streetAddress":"4289 Joesph Plaza","streetSuffix":"Highway","streetPrefix":"a","secondaryAddress":"Suite 874","county":"Cambridgeshire","country":"Angola","state":"Illinois","latitude":"1.1052","longitude":"-147.8694"}}