{"id":"3ea290c6-6b80-4e6a-a91e-0d375f5737ee","color":"#075b17","image":"http://lorempixel.com/640/480/business","name":"Sipes, Zulauf and Gleichner","suffice":"and Sons","catchPhrase":"Expanded 24/7 leverage","bs":"best-of-breed seize technologies","address":{"zipCode":"99002","city":"Leefurt","cityPrefix":"Lake","citySuffix":"fort","streetName":"Nicola Island","streetAddress":"14395 Connelly Freeway","streetSuffix":"Heights","streetPrefix":"a","secondaryAddress":"Suite 571","county":"Cambridgeshire","country":"Christmas Island","state":"Iowa","latitude":"-0.7635","longitude":"62.0352"}}