{"id":"43c866e2-e96e-4d6f-9174-9116681920b3","color":"#052965","image":"http://lorempixel.com/640/480/business","name":"Tremblay Group","suffice":"Group","catchPhrase":"Secured methodical knowledge user","bs":"end-to-end integrate interfaces","address":{"zipCode":"80296-0967","city":"Lake Sherman","cityPrefix":"Port","citySuffix":"mouth","streetName":"Jimmy Prairie","streetAddress":"173 Reichel Path","streetSuffix":"Valley","streetPrefix":"c","secondaryAddress":"Suite 156","county":"Bedfordshire","country":"Aruba","state":"Indiana","latitude":"-6.4396","longitude":"124.3173"}}