{"id":"44869a20-c046-4ae7-9f3b-344250ce7a3b","color":"#014735","image":"http://lorempixel.com/640/480/business","name":"Miller Group","suffice":"Group","catchPhrase":"Function-based executive matrices","bs":"best-of-breed cultivate applications","address":{"zipCode":"38588","city":"Weimannland","cityPrefix":"East","citySuffix":"town","streetName":"Gutkowski Road","streetAddress":"558 Nora Squares","streetSuffix":"Falls","streetPrefix":"a","secondaryAddress":"Suite 394","county":"Berkshire","country":"Antarctica (the territory South of 60 deg S)","state":"Oregon","latitude":"-13.9200","longitude":"-96.3630"}}