{"id":"4d20feaf-c71f-4702-ae69-11bc06507048","color":"#0e0c0a","image":"http://lorempixel.com/640/480/business","name":"Runolfsson Inc","suffice":"and Sons","catchPhrase":"Profit-focused responsive paradigm","bs":"one-to-one reintermediate supply-chains","address":{"zipCode":"45379-8599","city":"Xandermouth","cityPrefix":"Port","citySuffix":"burgh","streetName":"Robbie Meadow","streetAddress":"512 Denesik Knoll","streetSuffix":"Via","streetPrefix":"c","secondaryAddress":"Apt. 484","county":"Buckinghamshire","country":"Heard Island and McDonald Islands","state":"Alabama","latitude":"29.4685","longitude":"-84.0623"}}