{"id":"4ed1ab51-f944-4dc4-b3b0-1ba648f05bdc","color":"#7c042b","image":"http://lorempixel.com/640/480/business","name":"Ortiz Inc","suffice":"Group","catchPhrase":"Diverse stable definition","bs":"24/365 drive vortals","address":{"zipCode":"10957","city":"East Marinaville","cityPrefix":"Lake","citySuffix":"burgh","streetName":"Jaskolski Road","streetAddress":"6937 Connelly Walks","streetSuffix":"Valley","streetPrefix":"a","secondaryAddress":"Suite 107","county":"Borders","country":"British Indian Ocean Territory (Chagos Archipelago)","state":"Washington","latitude":"60.5784","longitude":"16.0009"}}