{"id":"5359f8ec-2ffb-48bb-abe6-1b45ae9a848f","color":"#7e5f19","image":"http://lorempixel.com/640/480/business","name":"Reilly Inc","suffice":"Group","catchPhrase":"Robust 3rd generation architecture","bs":"extensible syndicate e-markets","address":{"zipCode":"72434","city":"East Jedidiahbury","cityPrefix":"Lake","citySuffix":"port","streetName":"Miller Pike","streetAddress":"92510 Rocky Landing","streetSuffix":"Track","streetPrefix":"a","secondaryAddress":"Suite 321","county":"Berkshire","country":"Tokelau","state":"Massachusetts","latitude":"-4.6131","longitude":"-65.9195"}}