{"id":"57df5db2-3646-4999-a151-b6bd3e58dc53","color":"#226655","image":"http://lorempixel.com/640/480/business","name":"Kessler - Spencer","suffice":"Group","catchPhrase":"Team-oriented mission-critical hierarchy","bs":"holistic monetize content","address":{"zipCode":"12574-9098","city":"South Mara","cityPrefix":"Port","citySuffix":"furt","streetName":"Elyse Trail","streetAddress":"949 Boehm Crossing","streetSuffix":"Glen","streetPrefix":"c","secondaryAddress":"Suite 470","county":"Berkshire","country":"Turkmenistan","state":"Arkansas","latitude":"-16.1266","longitude":"149.6130"}}