{"id":"87f9d2b0-5493-4662-a102-1e3de85cc635","color":"#546f3f","image":"http://lorempixel.com/640/480/business","name":"Jones - Kunde","suffice":"Inc","catchPhrase":"Front-line motivating internet solution","bs":"world-class e-enable communities","address":{"zipCode":"21130-5035","city":"North Wernermouth","cityPrefix":"East","citySuffix":"burgh","streetName":"Magdalena Spring","streetAddress":"866 Mante Bridge","streetSuffix":"Gateway","streetPrefix":"b","secondaryAddress":"Apt. 107","county":"Cambridgeshire","country":"Australia","state":"Indiana","latitude":"-14.4201","longitude":"110.5549"}}