{"id":"9a7cd936-2d8e-49d3-82ef-414720d64996","color":"#76541a","image":"http://lorempixel.com/640/480/business","name":"Goyette, Kunze and Zieme","suffice":"Group","catchPhrase":"Ergonomic zero administration hardware","bs":"wireless enhance initiatives","address":{"zipCode":"20824-9795","city":"Janefurt","cityPrefix":"East","citySuffix":"shire","streetName":"Dickens Circles","streetAddress":"7740 Klein River","streetSuffix":"Squares","streetPrefix":"b","secondaryAddress":"Suite 434","county":"Cambridgeshire","country":"Brunei Darussalam","state":"North Carolina","latitude":"-28.7349","longitude":"147.5670"}}