{"id":"a81ce557-8f39-4805-bef8-8b2bb9d1ae38","color":"#4a636a","image":"http://lorempixel.com/640/480/business","name":"Schamberger - Rosenbaum","suffice":"Group","catchPhrase":"Open-source background utilisation","bs":"global revolutionize mindshare","address":{"zipCode":"88689","city":"Port Jarretbury","cityPrefix":"Lake","citySuffix":"borough","streetName":"Michele Mall","streetAddress":"83067 Rogahn Trace","streetSuffix":"Plain","streetPrefix":"c","secondaryAddress":"Suite 555","county":"Bedfordshire","country":"Belgium","state":"Connecticut","latitude":"15.5744","longitude":"-99.3279"}}