{"id":"ab1a9fe2-0e70-47b8-884e-357cb560f855","color":"#3b4c14","image":"http://lorempixel.com/640/480/business","name":"Koelpin - Ledner","suffice":"Inc","catchPhrase":"Face to face clear-thinking policy","bs":"bricks-and-clicks mesh experiences","address":{"zipCode":"45379","city":"Susiestad","cityPrefix":"South","citySuffix":"borough","streetName":"Ronny Common","streetAddress":"4511 Carroll Parks","streetSuffix":"Street","streetPrefix":"b","secondaryAddress":"Suite 054","county":"Buckinghamshire","country":"Vanuatu","state":"Florida","latitude":"-57.1743","longitude":"58.3747"}}