{"id":"af4dd961-4e6f-48fc-8c29-ca87b414a16c","color":"#18512a","image":"http://lorempixel.com/640/480/business","name":"Nienow Inc","suffice":"and Sons","catchPhrase":"Open-source bottom-line success","bs":"best-of-breed disintermediate supply-chains","address":{"zipCode":"37540","city":"South Kaylieton","cityPrefix":"Lake","citySuffix":"town","streetName":"Osborne Shore","streetAddress":"52499 McGlynn Fields","streetSuffix":"Fords","streetPrefix":"a","secondaryAddress":"Apt. 523","county":"Avon","country":"Slovakia (Slovak Republic)","state":"Arkansas","latitude":"77.4049","longitude":"-119.0065"}}