{"id":"c55c8c06-2faf-4c35-bc39-ce888cf99196","color":"#40412a","image":"http://lorempixel.com/640/480/business","name":"Labadie, Strosin and Gibson","suffice":"LLC","catchPhrase":"Fully-configurable object-oriented adapter","bs":"cutting-edge embrace ROI","address":{"zipCode":"85379","city":"South Janetfurt","cityPrefix":"New","citySuffix":"ville","streetName":"Jada Inlet","streetAddress":"60462 Eugenia Unions","streetSuffix":"Springs","streetPrefix":"c","secondaryAddress":"Apt. 683","county":"Avon","country":"Bolivia","state":"Oklahoma","latitude":"56.6635","longitude":"-61.0052"}}