{"id":"cf629b9c-dac1-44e5-ab40-88389a320c48","color":"#181206","image":"http://lorempixel.com/640/480/business","name":"Crist, Zulauf and Weimann","suffice":"Inc","catchPhrase":"Intuitive coherent budgetary management","bs":"leading-edge architect metrics","address":{"zipCode":"67578-6608","city":"East Vitaton","cityPrefix":"Port","citySuffix":"furt","streetName":"Libbie Bridge","streetAddress":"288 Thompson Causeway","streetSuffix":"Green","streetPrefix":"a","secondaryAddress":"Apt. 182","county":"Cambridgeshire","country":"Uzbekistan","state":"Arizona","latitude":"80.0876","longitude":"93.9009"}}