{"id":"d25733d3-d81e-41e1-9085-842da956827e","color":"#400a66","image":"http://lorempixel.com/640/480/business","name":"Wyman and Sons","suffice":"Group","catchPhrase":"Proactive scalable product","bs":"world-class exploit metrics","address":{"zipCode":"45480-4608","city":"Lake Kamronville","cityPrefix":"West","citySuffix":"haven","streetName":"Spencer Heights","streetAddress":"0242 Gerardo Corners","streetSuffix":"Mountains","streetPrefix":"b","secondaryAddress":"Suite 211","county":"Cambridgeshire","country":"Ecuador","state":"Florida","latitude":"-80.3709","longitude":"-23.5726"}}